mohinh/__init__.py
mohinh/mohinh.py
mohinh-2.0.0.dist-info/LICENSE
mohinh-2.0.0.dist-info/METADATA
mohinh-2.0.0.dist-info/WHEEL
mohinh-2.0.0.dist-info/top_level.txt
mohinh-2.0.0.dist-info/RECORD
