Metadata-Version: 2.1
Name: mohinh
Version: 2.0.0
Summary: A model builder package
Home-page: https://github.com/robinthibaut/mohinh
Author: Robin Thibaut
Author-email: Robin.Thibaut@UGent.be
License: UNKNOWN
Platform: UNKNOWN
Classifier: Programming Language :: Python :: 3
Classifier: License :: OSI Approved :: MIT License
Classifier: Operating System :: OS Independent
Requires-Python: >=3.6
Requires-Dist: numpy
Requires-Dist: matplotlib
